Unsiloed/__init__.py
Unsiloed/main.py
Unsiloed/routes/__init__.py
Unsiloed/routes/chunking_routes.py
Unsiloed/routes/root_routes.py
Unsiloed/services/chunking.py
Unsiloed/utils/__init__.py
Unsiloed/utils/chunking.py
Unsiloed/utils/openai.py
unsiloed-0.1.3.dist-info/licenses/LICENSE
unsiloed-0.1.3.dist-info/METADATA
unsiloed-0.1.3.dist-info/WHEEL
unsiloed-0.1.3.dist-info/entry_points.txt
unsiloed-0.1.3.dist-info/top_level.txt
unsiloed-0.1.3.dist-info/RECORD
