Metadata-Version: 2.4
Name: Unsiloed
Version: 0.1.3
Summary: A super simple way to extract text from documents for for intelligent document processing, extraction, and chunking with multi-threaded processing capabilities
Home-page: https://github.com/Unsiloed-AI/Unsiloed-chunker
Author: Unsiloed AI
Author-email: hello@unsiloed-ai.com
Classifier: Programming Language :: Python :: 3
Classifier: License :: OSI Approved :: Apache Software License
Classifier: Operating System :: OS Independent
Requires-Python: >=3.8
License-File: LICENSE
Requires-Dist: uvicorn
Requires-Dist: fastapi
Requires-Dist: python-multipart
Requires-Dist: python-dotenv
Requires-Dist: pdf2image
Requires-Dist: Pillow
Requires-Dist: PyPDF2
Requires-Dist: python-docx
Requires-Dist: python-pptx
Requires-Dist: openai
Requires-Dist: numpy
Requires-Dist: opencv-python-headless
Requires-Dist: requests
Dynamic: author
Dynamic: author-email
Dynamic: classifier
Dynamic: description
Dynamic: description-content-type
Dynamic: home-page
Dynamic: license-file
Dynamic: requires-dist
Dynamic: requires-python
Dynamic: summary
